stlrcore/__init__.py
stlrcore/audio_utils.py
stlrcore/transcribe.py
stlrcore/transcription_models.py
stlrcore-1.0.1.dist-info/METADATA
stlrcore-1.0.1.dist-info/WHEEL
stlrcore-1.0.1.dist-info/licenses/LICENSE
stlrcore-1.0.1.dist-info/RECORD
