Metadata-Version: 2.1
Name: stlrcore
Version: 1.0.1
Summary: Create and process audio transcriptions with word timings
Project-URL: Homepage, https://github.com/lilellia/stlr
Author-email: Lily Ellington <pixielf.0@gmail.com>
License-File: LICENSE
Classifier: Development Status :: 4 - Beta
Classifier: License :: OSI Approved :: MIT License
Classifier: Operating System :: OS Independent
Classifier: Programming Language :: Python :: 3
Requires-Python: >=3.11
Requires-Dist: attrs
Requires-Dist: ffmpeg-python
Requires-Dist: pydub
Requires-Dist: stable-ts
Requires-Dist: tabulate
Requires-Dist: whisper-timestamped
